odoo/addons/sale_automatic_workflow_stock_job/README.rst
odoo/addons/sale_automatic_workflow_stock_job/__init__.py
odoo/addons/sale_automatic_workflow_stock_job/__manifest__.py
odoo/addons/sale_automatic_workflow_stock_job/data/queue_job_data.xml
odoo/addons/sale_automatic_workflow_stock_job/i18n/it.po
odoo/addons/sale_automatic_workflow_stock_job/i18n/sale_automatic_workflow_stock_job.pot
odoo/addons/sale_automatic_workflow_stock_job/models/__init__.py
odoo/addons/sale_automatic_workflow_stock_job/models/automatic_workflow_job.py
odoo/addons/sale_automatic_workflow_stock_job/readme/CONTRIBUTORS.md
odoo/addons/sale_automatic_workflow_stock_job/readme/CREDITS.md
odoo/addons/sale_automatic_workflow_stock_job/readme/DESCRIPTION.md
odoo/addons/sale_automatic_workflow_stock_job/static/description/icon.png
odoo/addons/sale_automatic_workflow_stock_job/static/description/index.html
odoo/addons/sale_automatic_workflow_stock_job/tests/__init__.py
odoo/addons/sale_automatic_workflow_stock_job/tests/test_auto_workflow_stock_job.py
odoo_addon_sale_automatic_workflow_stock_job-18.0.1.0.0.4.dist-info/METADATA
odoo_addon_sale_automatic_workflow_stock_job-18.0.1.0.0.4.dist-info/WHEEL
odoo_addon_sale_automatic_workflow_stock_job-18.0.1.0.0.4.dist-info/top_level.txt
odoo_addon_sale_automatic_workflow_stock_job-18.0.1.0.0.4.dist-info/RECORD
